selanneal/__init__.py
selanneal/annealing.py
selanneal/optimise.py
selanneal/utils.py
selanneal-0.0.4.dist-info/LICENSE
selanneal-0.0.4.dist-info/METADATA
selanneal-0.0.4.dist-info/WHEEL
selanneal-0.0.4.dist-info/top_level.txt
selanneal-0.0.4.dist-info/RECORD
