Metadata-Version: 2.1
Name: selanneal
Version: 0.0.4
Summary: multidimensional selection optimisation with simulated annealing
Home-page: https://github.com/feichtip/selanneal
Author: Paul Feichtinger
Author-email: paul.feichtinger@oeaw.ac.at
License: MIT
Project-URL: Source, https://github.com/feichtip/selanneal
Project-URL: Tracker, https://github.com/feichtip/selanneal/issues
Keywords: hep physics cut selection optimisation annealing
Classifier: Programming Language :: Python :: 3
Classifier: License :: OSI Approved :: MIT License
Classifier: Operating System :: OS Independent
Requires-Python: >=3.6
License-File: LICENSE
Requires-Dist: numpy>=1.18.0
Requires-Dist: numba>=0.53.0
